robotstatuschecker.py
robotstatuschecker-4.1.0.dist-info/METADATA
robotstatuschecker-4.1.0.dist-info/WHEEL
robotstatuschecker-4.1.0.dist-info/top_level.txt
robotstatuschecker-4.1.0.dist-info/RECORD
