Metadata-Version: 2.2
Name: robotstatuschecker
Version: 4.1.0
Summary: A tool for checking that Robot Framework test cases have expected statuses and log messages.
Home-page: https://github.com/robotframework/statuschecker
Download-URL: https://pypi.python.org/pypi/robotstatuschecker
Author: Robot Framework Developers
Author-email: robotframework@gmail.com
License: Apache License 2.0
Keywords: robotframework testing testautomation atdd
Platform: any
Classifier: Development Status :: 5 - Production/Stable
Classifier: License :: OSI Approved :: Apache Software License
Classifier: Operating System :: OS Independent
Classifier: Programming Language :: Python :: 3
Classifier: Topic :: Software Development :: Testing
Classifier: Framework :: Robot Framework
Requires-Python: >=3.6,<4.0
Requires-Dist: robotframework
Dynamic: author
Dynamic: author-email
Dynamic: classifier
Dynamic: description
Dynamic: download-url
Dynamic: home-page
Dynamic: keywords
Dynamic: license
Dynamic: platform
Dynamic: requires-dist
Dynamic: requires-python
Dynamic: summary
